LICENSE
MANIFEST.in
README.md
setup.py
django_etl/__init__.py
django_etl/admin.py
django_etl/core.py
django_etl/models.py
django_etl/tests.py
django_etl/views.py
django_etl.egg-info/PKG-INFO
django_etl.egg-info/SOURCES.txt
django_etl.egg-info/dependency_links.txt
django_etl.egg-info/requires.txt
django_etl.egg-info/top_level.txt
django_etl/management/__init__.py
django_etl/management/commands/__init__.py
django_etl/management/commands/run_etl.py
docs/changelog.md