Metadata-Version: 1.1
Name: django-etl
Version: 0.1.0
Summary: A Django application that provides a management command to make using the petl library easier.
Home-page: https://github.com/PGower/django_etl
Author: Paul Gower
Author-email: p.gower@gmail.com
License: UNKNOWN
Download-URL: https://github.com/PGower/django_etl/releases
Keywords: django,petl,etl,synchronize,sync,extract,transform,load
Platform: UNKNOWN
Classifier: Development Status :: 3 - Alpha
Classifier: Environment :: Web Environment
Classifier: Programming Language :: Python
Classifier: Framework :: Django
Classifier: Intended Audience :: Developers
Classifier: License :: OSI Approved :: Apache Software License
Classifier: Operating System :: OS Independent
Classifier: Topic :: Database
Classifier: Topic :: Software Development :: Libraries :: Python Modules
